bluequbit/__init__.py
bluequbit/backend_connection.py
bluequbit/bluequbit_client.py
bluequbit/bluequbit_logger.py
bluequbit/check_version.py
bluequbit/circuit_serialization.py
bluequbit/computation_local.py
bluequbit/estimate_result.py
bluequbit/exceptions.py
bluequbit/file_utils.py
bluequbit/host_info.py
bluequbit/http_utils.py
bluequbit/job_metadata_constants.py
bluequbit/job_result.py
bluequbit/local_execution.py
bluequbit/tools.py
bluequbit/version.py
bluequbit/api/__init__.py
bluequbit/api/jobs.py
bluequbit/library/__init__.py
bluequbit/library/utils.py
bluequbit/library/circuits/__init__.py
bluequbit/library/circuits/bell_pair.py
bluequbit/library/circuits/coin_toss.py
bluequbit/library/circuits/draper_adder.py
bluequbit/library/circuits/ghz.py
bluequbit/library/circuits/multi_adder.py
bluequbit/library/circuits/qft.py
bluequbit/library/circuits/random_circuit.py
bluequbit/library/circuits/tfim_2d_grid.py
bluequbit/library/fidelity_estimator/__init__.py
bluequbit/library/fidelity_estimator/fidelity_estimation.py
bluequbit/library/fidelity_estimator/ibm_fez_calibration.json.gz
bluequbit/library/fidelity_estimator/ibm_fez_fidelity_estimation.py
bluequbit/library/fidelity_estimator/quantinuum_h2_fidelity_estimation.py
bluequbit/library/fidelity_estimator/save_ibm_fez_calibration_data.py
bluequbit/library/helpers/__init__.py
bluequbit/library/helpers/data_loader.py
bluequbit/library/helpers/hardware_connectivites.py
bluequbit/library/helpers/image.py
bluequbit/library/helpers/image_block_splitting_quantum.py
bluequbit/library/helpers/pauli_sum.py
bluequbit/pennylane_plugin/__init__.py
bluequbit/pennylane_plugin/bluequbit_cpu.py
bluequbit/pennylane_plugin/bluequbit_device.py
bluequbit/pennylane_plugin/bluequbit_gpu.py
bluequbit/qiskit_provider/__init__.py
bluequbit/qiskit_provider/backend.py
bluequbit/qiskit_provider/estimator.py
bluequbit/qiskit_provider/job.py
bluequbit/qiskit_provider/provider.py
bluequbit/qiskit_provider/sampler.py
bluequbit-0.18.1b1.dist-info/licenses/LICENSE
bluequbit-0.18.1b1.dist-info/METADATA
bluequbit-0.18.1b1.dist-info/WHEEL
bluequbit-0.18.1b1.dist-info/entry_points.txt
bluequbit-0.18.1b1.dist-info/top_level.txt
bluequbit-0.18.1b1.dist-info/RECORD
