Metadata-Version: 2.4
Name: bluequbit
Version: 0.18.1b1
Summary: Python SDK to BlueQubit app
Author-email: BlueQubit <hovnatan@bluequbit.io>
License-Expression: Apache-2.0
Project-URL: Homepage, https://app.bluequbit.io
Project-URL: Documentation, https://app.bluequbit.io/docs
Project-URL: SDK Reference, https://app.bluequbit.io/sdk-docs
Classifier: Programming Language :: Python
Classifier: Programming Language :: Python :: 3
Classifier: Programming Language :: Python :: 3.10
Classifier: Programming Language :: Python :: 3.11
Classifier: Programming Language :: Python :: 3.12
Classifier: Programming Language :: Python :: 3.13
Requires-Python: >=3.10
License-File: LICENSE
Requires-Dist: requests~=2.28
Requires-Dist: python-dateutil~=2.8
Requires-Dist: numpy>=1.21
Requires-Dist: packaging
Provides-Extra: qiskit
Requires-Dist: qiskit>=1.0; extra == "qiskit"
Provides-Extra: cirq
Requires-Dist: cirq>=1.0; extra == "cirq"
Provides-Extra: pennylane
Requires-Dist: pennylane>=0.39.0; extra == "pennylane"
Requires-Dist: pennylane-lightning>=0.39.0; extra == "pennylane"
Dynamic: description
Dynamic: description-content-type
Dynamic: license-file
